setup.py
GDistributions/Binomialdistribution.py
GDistributions/Gaussiandistribution.py
GDistributions/Generaldistribution.py
GDistributions/__init__.py
GDistributions.egg-info/PKG-INFO
GDistributions.egg-info/SOURCES.txt
GDistributions.egg-info/dependency_links.txt
GDistributions.egg-info/not-zip-safe
GDistributions.egg-info/top_level.txt